{
  "title": "Why Mindset is Everything",
  "segments": [
    {
      "text": "Your mindset shapes your reality.",
      "keywords": "clouds sunrise vision"
    },
    {
      "text": "Positivity breeds opportunity and growth.",
      "keywords": "flourishing plant sunlight"
    },
    {
      "text": "Replace self-doubt with self-belief.",
      "keywords": "confident individual"
    },
    {
      "text": "Challenge your limitations; they exist only in your mind.",
      "keywords": "breaking chains"
    },
    {
      "text": "Visualize your success and work toward it daily.",
      "keywords": "goal setting vision"
    },
    {
      "text": "Remember, you become what you think.",
      "keywords": "thoughtful person"
    },
    {
      "text": "Follow for your daily dose of discipline.",
      "keywords": "person looking up"
    }
  ],
  "description": "Your mindset determines your path to success. Follow for daily discipline! 🔮",
  "hashtags": [
    "#motivation",
    "#mindset",
    "#discipline",
    "#selfgrowth",
    "#shorts",
    "#fyp"
  ]
}